[
    {
        "id": "122211776",
        "premium": false,
        "name": "Главный редактор, Ozon Банк",
        "department": {
            "id": "ozonru-2180-fintech",
            "name": "Ozon Банк"
        },
        "has_test": false,
        "response_letter_required": false,
        "area": {
            "id": "1",
            "name": "Москва",
            "url": "https://api.hh.ru/areas/1"
        },
        "salary": null,
        "salary_range": null,
        "type": {
            "id": "open",
            "name": "Открытая"
        },
        "address": {
            "city": "Москва",
            "street": "Пресненская набережная",
            "building": "10",
            "lat": 55.74723295660558,
            "lng": 37.536558290665916,
            "description": null,
            "raw": "Москва, Пресненская набережная, 10",
            "metro": {
                "station_name": "Деловой центр",
                "line_name": "Большая кольцевая линия",
                "station_id": "97.603",
                "line_id": "97",
                "lat": 55.7491,
                "lng": 37.5395
            },
            "metro_stations": [
                {
                    "station_name": "Деловой центр",
                    "line_name": "Большая кольцевая линия",
                    "station_id": "97.603",
                    "line_id": "97",
                    "lat": 55.7491,
                    "lng": 37.5395
                },
                {
                    "station_name": "Деловой центр",
                    "line_name": "Солнцевская",
                    "station_id": "133.468",
                    "line_id": "133",
                    "lat": 55.7491,
                    "lng": 37.5395
                },
                {
                    "station_name": "Москва-Сити",
                    "line_name": "Филевская",
                    "station_id": "4.179",
                    "line_id": "4",
                    "lat": 55.748056,
                    "lng": 37.532778
                }
            ],
            "id": "1522426"
        },
        "response_url": null,
        "sort_point_distance": null,
        "published_at": "2025-06-30T15:07:20+0300",
        "created_at": "2025-06-30T15:07:20+0300",
        "archived": false,
        "apply_alternate_url": "https://hh.ru/applicant/vacancy_response?vacancyId=122211776",
        "branding": {
            "type": "MAKEUP",
            "tariff": null
        },
        "show_logo_in_search": true,
        "show_contacts": false,
        "insider_interview": null,
        "url": "https://api.hh.ru/vacancies/122211776?host=hh.ru",
        "alternate_url": "https://hh.ru/vacancy/122211776",
        "relations": [],
        "employer": {
            "id": "2180",
            "name": "Ozon",
            "url": "https://api.hh.ru/employers/2180",
            "alternate_url": "https://hh.ru/employer/2180",
            "logo_urls": {
                "original": "https://img.hhcdn.ru/employer-logo-original/1069622.png",
                "90": "https://img.hhcdn.ru/employer-logo/5899117.png",
                "240": "https://img.hhcdn.ru/employer-logo/5899118.png"
            },
            "vacancies_url": "https://api.hh.ru/vacancies?employer_id=2180",
            "accredited_it_employer": true,
            "employer_rating": {
                "total_rating": "4.6",
                "reviews_count": 9209
            },
            "trusted": true
        },
        "snippet": {
            "requirement": "Работали главным редактором не менее двух лет. Готовы разбираться в банковских продуктах и сервисах. Ответственны, проактивны, умеете находить общий язык...",
            "responsibility": "Управлять командой (6 человек): копирайтеры и UX-редакторы, отвечать за развитие каждого члена команды. Внедрять стандарты качества текстов и креатива..."
        },
        "contacts": null,
        "schedule": {
            "id": "fullDay",
            "name": "Полный день"
        },
        "working_days": [],
        "working_time_intervals": [],
        "working_time_modes": [],
        "accept_temporary": false,
        "fly_in_fly_out_duration": [],
        "work_format": [
            {
                "id": "ON_SITE",
                "name": "На месте работодателя"
            },
            {
                "id": "HYBRID",
                "name": "Гибрид"
            }
        ],
        "working_hours": [
            {
                "id": "HOURS_8",
                "name": "8 часов"
            }
        ],
        "work_schedule_by_days": [
            {
                "id": "FIVE_ON_TWO_OFF",
                "name": "5/2"
            }
        ],
        "night_shifts": false,
        "professional_roles": [
            {
                "id": "55",
                "name": "Копирайтер, редактор, корректор"
            }
        ],
        "accept_incomplete_resumes": false,
        "experience": {
            "id": "between3And6",
            "name": "От 3 до 6 лет"
        },
        "employment": {
            "id": "full",
            "name": "Полная занятость"
        },
        "employment_form": {
            "id": "FULL",
            "name": "Полная"
        },
        "internship": false,
        "adv_response_url": null,
        "is_adv_vacancy": false,
        "adv_context": null
    },
    {
        "id": "122204174",
        "premium": false,
        "name": "Старший разработчик Frontend, Ozon Банк",
        "department": {
            "id": "ozonru-2180-fintech",
            "name": "Ozon Банк"
        },
        "has_test": false,
        "response_letter_required": false,
        "area": {
            "id": "1",
            "name": "Москва",
            "url": "https://api.hh.ru/areas/1"
        },
        "salary": null,
        "salary_range": null,
        "type": {
            "id": "open",
            "name": "Открытая"
        },
        "address": {
            "city": "Москва",
            "street": "Пресненская набережная",
            "building": "10блокС",
            "lat": 55.747074,
            "lng": 37.536589,
            "description": null,
            "raw": "Москва, Пресненская набережная, 10блокС",
            "metro": null,
            "metro_stations": [],
            "id": "1481074"
        },
        "response_url": null,
        "sort_point_distance": null,
        "published_at": "2025-06-30T13:19:59+0300",
        "created_at": "2025-06-30T13:19:59+0300",
        "archived": false,
        "apply_alternate_url": "https://hh.ru/applicant/vacancy_response?vacancyId=122204174",
        "branding": {
            "type": "MAKEUP",
            "tariff": null
        },
        "show_logo_in_search": true,
        "show_contacts": false,
        "insider_interview": null,
        "url": "https://api.hh.ru/vacancies/122204174?host=hh.ru",
        "alternate_url": "https://hh.ru/vacancy/122204174",
        "relations": [],
        "employer": {
            "id": "2180",
            "name": "Ozon",
            "url": "https://api.hh.ru/employers/2180",
            "alternate_url": "https://hh.ru/employer/2180",
            "logo_urls": {
                "original": "https://img.hhcdn.ru/employer-logo-original/1069622.png",
                "90": "https://img.hhcdn.ru/employer-logo/5899117.png",
                "240": "https://img.hhcdn.ru/employer-logo/5899118.png"
            },
            "vacancies_url": "https://api.hh.ru/vacancies?employer_id=2180",
            "accredited_it_employer": true,
            "employer_rating": {
                "total_rating": "4.6",
                "reviews_count": 9209
            },
            "trusted": true
        },
        "snippet": {
            "requirement": "Опыт работы с JavaScript (ECMA 5/6) и понимание, как устроено прототипное наследование, зачем нужны замыкания и что такое контекст. ",
            "responsibility": "Команда Банка Ozon создаёт и развивает сервисы для покупателей и продавцов. Мы строим банк как современный IT-продукт — с передовыми..."
        },
        "contacts": null,
        "schedule": {
            "id": "remote",
            "name": "Удаленная работа"
        },
        "working_days": [],
        "working_time_intervals": [],
        "working_time_modes": [],
        "accept_temporary": false,
        "fly_in_fly_out_duration": [],
        "work_format": [
            {
                "id": "ON_SITE",
                "name": "На месте работодателя"
            },
            {
                "id": "REMOTE",
                "name": "Удалённо"
            },
            {
                "id": "HYBRID",
                "name": "Гибрид"
            }
        ],
        "working_hours": [
            {
                "id": "HOURS_8",
                "name": "8 часов"
            }
        ],
        "work_schedule_by_days": [
            {
                "id": "FIVE_ON_TWO_OFF",
                "name": "5/2"
            }
        ],
        "night_shifts": false,
        "professional_roles": [
            {
                "id": "96",
                "name": "Программист, разработчик"
            }
        ],
        "accept_incomplete_resumes": false,
        "experience": {
            "id": "between3And6",
            "name": "От 3 до 6 лет"
        },
        "employment": {
            "id": "full",
            "name": "Полная занятость"
        },
        "employment_form": {
            "id": "FULL",
            "name": "Полная"
        },
        "internship": false,
        "adv_response_url": null,
        "is_adv_vacancy": false,
        "adv_context": null
    },
    {
        "id": "122106052",
        "premium": false,
        "name": "Водитель-курьер (Омск)",
        "department": {
            "id": "ozonru-2180-boro",
            "name": "Ozon Производство"
        },
        "has_test": false,
        "response_letter_required": false,
        "area": {
            "id": "68",
            "name": "Омск",
            "url": "https://api.hh.ru/areas/68"
        },
        "salary": {
            "from": 201000,
            "to": 378000,
            "currency": "RUR",
            "gross": true
        },
        "salary_range": {
            "from": 201000,
            "to": 378000,
            "currency": "RUR",
            "gross": true,
            "mode": {
                "id": "MONTH",
                "name": "За месяц"
            },
            "frequency": null
        },
        "type": {
            "id": "open",
            "name": "Открытая"
        },
        "address": {
            "city": "Омск",
            "street": "улица Айвазовского",
            "building": "31",
            "lat": 54.997605,
            "lng": 73.169469,
            "description": null,
            "raw": "Омск, улица Айвазовского, 31",
            "metro": null,
            "metro_stations": [],
            "id": "15847291"
        },
        "response_url": null,
        "sort_point_distance": null,
        "published_at": "2025-06-26T15:26:32+0300",
        "created_at": "2025-06-26T15:26:32+0300",
        "archived": false,
        "apply_alternate_url": "https://hh.ru/applicant/vacancy_response?vacancyId=122106052",
        "branding": {
            "type": "MAKEUP",
            "tariff": null
        },
        "show_logo_in_search": true,
        "show_contacts": true,
        "insider_interview": null,
        "url": "https://api.hh.ru/vacancies/122106052?host=hh.ru",
        "alternate_url": "https://hh.ru/vacancy/122106052",
        "relations": [],
        "employer": {
            "id": "2180",
            "name": "Ozon",
            "url": "https://api.hh.ru/employers/2180",
            "alternate_url": "https://hh.ru/employer/2180",
            "logo_urls": {
                "original": "https://img.hhcdn.ru/employer-logo-original/1069622.png",
                "90": "https://img.hhcdn.ru/employer-logo/5899117.png",
                "240": "https://img.hhcdn.ru/employer-logo/5899118.png"
            },
            "vacancies_url": "https://api.hh.ru/vacancies?employer_id=2180",
            "accredited_it_employer": true,
            "employer_rating": {
                "total_rating": "4.6",
                "reviews_count": 9209
            },
            "trusted": true
        },
        "snippet": {
            "requirement": "Вместительный грузовой личный автомобиль для осуществления доставок (от 8 паллет до 12 паллет). Водительские права категории В. Телефон на базе...",
            "responsibility": "Доставлять товары интернет-магазина в пункты выдачи заказов на личном грузовом автомобиле. Забирать возвраты из пункта выдачи заказов. "
        },
        "contacts": null,
        "schedule": {
            "id": "shift",
            "name": "Сменный график"
        },
        "working_days": [],
        "working_time_intervals": [],
        "working_time_modes": [],
        "accept_temporary": false,
        "fly_in_fly_out_duration": [],
        "work_format": [],
        "working_hours": [
            {
                "id": "HOURS_12",
                "name": "12 часов"
            }
        ],
        "work_schedule_by_days": [
            {
                "id": "TWO_ON_TWO_OFF",
                "name": "2/2"
            }
        ],
        "night_shifts": false,
        "professional_roles": [
            {
                "id": "58",
                "name": "Курьер"
            }
        ],
        "accept_incomplete_resumes": false,
        "experience": {
            "id": "noExperience",
            "name": "Нет опыта"
        },
        "employment": {
            "id": "full",
            "name": "Полная занятость"
        },
        "employment_form": {
            "id": "FULL",
            "name": "Полная"
        },
        "internship": false,
        "adv_response_url": null,
        "is_adv_vacancy": false,
        "adv_context": null
    },
    {
        "id": "122185173",
        "premium": false,
        "name": "Специалист по документообороту",
        "department": {
            "id": "ozonru-2180-express",
            "name": "Ozon fresh"
        },
        "has_test": false,
        "response_letter_required": false,
        "area": {
            "id": "53",
            "name": "Краснодар",
            "url": "https://api.hh.ru/areas/53"
        },
        "salary": {
            "from": 49500,
            "to": null,
            "currency": "RUR",
            "gross": true
        },
        "salary_range": {
            "from": 49500,
            "to": null,
            "currency": "RUR",
            "gross": true,
            "mode": {
                "id": "MONTH",
                "name": "За месяц"
            },
            "frequency": null
        },
        "type": {
            "id": "open",
            "name": "Открытая"
        },
        "address": {
            "city": "Краснодар",
            "street": "улица Стасова",
            "building": "178",
            "lat": 45.027438,
            "lng": 39.044205,
            "description": null,
            "raw": "Краснодар, улица Стасова, 178",
            "metro": null,
            "metro_stations": [],
            "id": "16026361"
        },
        "response_url": null,
        "sort_point_distance": null,
        "published_at": "2025-06-30T09:31:02+0300",
        "created_at": "2025-06-30T09:31:02+0300",
        "archived": false,
        "apply_alternate_url": "https://hh.ru/applicant/vacancy_response?vacancyId=122185173",
        "branding": {
            "type": "MAKEUP",
            "tariff": null
        },
        "show_logo_in_search": true,
        "show_contacts": true,
        "insider_interview": null,
        "url": "https://api.hh.ru/vacancies/122185173?host=hh.ru",
        "alternate_url": "https://hh.ru/vacancy/122185173",
        "relations": [],
        "employer": {
            "id": "2180",
            "name": "Ozon",
            "url": "https://api.hh.ru/employers/2180",
            "alternate_url": "https://hh.ru/employer/2180",
            "logo_urls": {
                "original": "https://img.hhcdn.ru/employer-logo-original/1069622.png",
                "90": "https://img.hhcdn.ru/employer-logo/5899117.png",
                "240": "https://img.hhcdn.ru/employer-logo/5899118.png"
            },
            "vacancies_url": "https://api.hh.ru/vacancies?employer_id=2180",
            "accredited_it_employer": true,
            "employer_rating": {
                "total_rating": "4.6",
                "reviews_count": 9209
            },
            "trusted": true
        },
        "snippet": {
            "requirement": "Желателен опыт ведения документооборота. Уверенный пользователь ПК (в том числе Microsoft Excel). Ответственность, внимательность, коммуникабельность.",
            "responsibility": "Проведение медосмотров за счет компании. Вам предстоит: Работа с первичной документацией. Кадровый документооборот: переводы, увольнения, отпуска. Ведение складского документооборота. "
        },
        "contacts": null,
        "schedule": {
            "id": "fullDay",
            "name": "Полный день"
        },
        "working_days": [],
        "working_time_intervals": [],
        "working_time_modes": [],
        "accept_temporary": false,
        "fly_in_fly_out_duration": [],
        "work_format": [],
        "working_hours": [
            {
                "id": "HOURS_8",
                "name": "8 часов"
            }
        ],
        "work_schedule_by_days": [
            {
                "id": "FIVE_ON_TWO_OFF",
                "name": "5/2"
            }
        ],
        "night_shifts": false,
        "professional_roles": [
            {
                "id": "33",
                "name": "Делопроизводитель, архивариус"
            }
        ],
        "accept_incomplete_resumes": false,
        "experience": {
            "id": "noExperience",
            "name": "Нет опыта"
        },
        "employment": {
            "id": "full",
            "name": "Полная занятость"
        },
        "employment_form": {
            "id": "FULL",
            "name": "Полная"
        },
        "internship": false,
        "adv_response_url": null,
        "is_adv_vacancy": false,
        "adv_context": null
    },
    {
        "id": "122206008",
        "premium": false,
        "name": "Аналитик данных, Маркетплейс, Отдел продуктовой аналитики",
        "department": {
            "id": "ozonru-2180-dev",
            "name": "Ozon Информационные технологии"
        },
        "has_test": false,
        "response_letter_required": false,
        "area": {
            "id": "1",
            "name": "Москва",
            "url": "https://api.hh.ru/areas/1"
        },
        "salary": null,
        "salary_range": null,
        "type": {
            "id": "open",
            "name": "Открытая"
        },
        "address": null,
        "response_url": null,
        "sort_point_distance": null,
        "published_at": "2025-06-30T13:48:44+0300",
        "created_at": "2025-06-30T13:48:44+0300",
        "archived": false,
        "apply_alternate_url": "https://hh.ru/applicant/vacancy_response?vacancyId=122206008",
        "branding": {
            "type": "MAKEUP",
            "tariff": null
        },
        "show_logo_in_search": true,
        "show_contacts": false,
        "insider_interview": null,
        "url": "https://api.hh.ru/vacancies/122206008?host=hh.ru",
        "alternate_url": "https://hh.ru/vacancy/122206008",
        "relations": [],
        "employer": {
            "id": "2180",
            "name": "Ozon",
            "url": "https://api.hh.ru/employers/2180",
            "alternate_url": "https://hh.ru/employer/2180",
            "logo_urls": {
                "original": "https://img.hhcdn.ru/employer-logo-original/1069622.png",
                "90": "https://img.hhcdn.ru/employer-logo/5899117.png",
                "240": "https://img.hhcdn.ru/employer-logo/5899118.png"
            },
            "vacancies_url": "https://api.hh.ru/vacancies?employer_id=2180",
            "accredited_it_employer": true,
            "employer_rating": {
                "total_rating": "4.6",
                "reviews_count": 9209
            },
            "trusted": true
        },
        "snippet": {
            "requirement": "Продуктовое мышление: понимание, как данные влияют на бизнес-решения. Продвинутый SQL: работа с миллионами строк, сложные JOIN, оконные функции, оптимизация...",
            "responsibility": "Формирование дерева метрик для оценки эффективности внутренних сервисов. Проектирование ETL-процессов (скорость, качество, алерты). Разработка регулярной отчётности в BI-инструментах. "
        },
        "contacts": null,
        "schedule": {
            "id": "remote",
            "name": "Удаленная работа"
        },
        "working_days": [],
        "working_time_intervals": [],
        "working_time_modes": [],
        "accept_temporary": false,
        "fly_in_fly_out_duration": [],
        "work_format": [
            {
                "id": "ON_SITE",
                "name": "На месте работодателя"
            },
            {
                "id": "REMOTE",
                "name": "Удалённо"
            },
            {
                "id": "HYBRID",
                "name": "Гибрид"
            }
        ],
        "working_hours": [
            {
                "id": "HOURS_8",
                "name": "8 часов"
            }
        ],
        "work_schedule_by_days": [
            {
                "id": "FIVE_ON_TWO_OFF",
                "name": "5/2"
            }
        ],
        "night_shifts": false,
        "professional_roles": [
            {
                "id": "156",
                "name": "BI-аналитик, аналитик данных"
            }
        ],
        "accept_incomplete_resumes": false,
        "experience": {
            "id": "between1And3",
            "name": "От 1 года до 3 лет"
        },
        "employment": {
            "id": "full",
            "name": "Полная занятость"
        },
        "employment_form": {
            "id": "FULL",
            "name": "Полная"
        },
        "internship": false,
        "adv_response_url": null,
        "is_adv_vacancy": false,
        "adv_context": null
    },
    {
        "id": "122207011",
        "premium": false,
        "name": "Специалист по логистике",
        "department": {
            "id": "ozonru-2180-boro",
            "name": "Ozon Производство"
        },
        "has_test": false,
        "response_letter_required": false,
        "area": {
            "id": "1",
            "name": "Москва",
            "url": "https://api.hh.ru/areas/1"
        },
        "salary": null,
        "salary_range": null,
        "type": {
            "id": "open",
            "name": "Открытая"
        },
        "address": {
            "city": "Москва",
            "street": "Пресненская набережная",
            "building": "10",
            "lat": 55.746593,
            "lng": 37.53738,
            "description": null,
            "raw": "Москва, Пресненская набережная, 10",
            "metro": {
                "station_name": "Деловой центр",
                "line_name": "Большая кольцевая линия",
                "station_id": "97.603",
                "line_id": "97",
                "lat": 55.7491,
                "lng": 37.5395
            },
            "metro_stations": [
                {
                    "station_name": "Деловой центр",
                    "line_name": "Большая кольцевая линия",
                    "station_id": "97.603",
                    "line_id": "97",
                    "lat": 55.7491,
                    "lng": 37.5395
                },
                {
                    "station_name": "Деловой центр",
                    "line_name": "Солнцевская",
                    "station_id": "133.468",
                    "line_id": "133",
                    "lat": 55.7491,
                    "lng": 37.5395
                },
                {
                    "station_name": "Москва-Сити",
                    "line_name": "Филевская",
                    "station_id": "4.179",
                    "line_id": "4",
                    "lat": 55.748056,
                    "lng": 37.532778
                }
            ],
            "id": "5799088"
        },
        "response_url": null,
        "sort_point_distance": null,
        "published_at": "2025-06-30T14:04:34+0300",
        "created_at": "2025-06-30T14:04:34+0300",
        "archived": false,
        "apply_alternate_url": "https://hh.ru/applicant/vacancy_response?vacancyId=122207011",
        "branding": {
            "type": "MAKEUP",
            "tariff": null
        },
        "show_logo_in_search": true,
        "show_contacts": false,
        "insider_interview": null,
        "url": "https://api.hh.ru/vacancies/122207011?host=hh.ru",
        "alternate_url": "https://hh.ru/vacancy/122207011",
        "relations": [],
        "employer": {
            "id": "2180",
            "name": "Ozon",
            "url": "https://api.hh.ru/employers/2180",
            "alternate_url": "https://hh.ru/employer/2180",
            "logo_urls": {
                "original": "https://img.hhcdn.ru/employer-logo-original/1069622.png",
                "90": "https://img.hhcdn.ru/employer-logo/5899117.png",
                "240": "https://img.hhcdn.ru/employer-logo/5899118.png"
            },
            "vacancies_url": "https://api.hh.ru/vacancies?employer_id=2180",
            "accredited_it_employer": true,
            "employer_rating": {
                "total_rating": "4.6",
                "reviews_count": 9209
            },
            "trusted": true
        },
        "snippet": {
            "requirement": "Средне-специальное или высшее образование. Опыт работы в логистике (желателен). Уверенный пользователь ПК, Excel (сводные таблицы, ВПР). Аналитический склад ума.",
            "responsibility": "Взаимодействие с транспортными компаниями и складами на предмет своевременной подачи ТС на загрузку/выгрузку. Распределение ТС по маршрутам. "
        },
        "contacts": null,
        "schedule": {
            "id": "shift",
            "name": "Сменный график"
        },
        "working_days": [],
        "working_time_intervals": [],
        "working_time_modes": [],
        "accept_temporary": false,
        "fly_in_fly_out_duration": [],
        "work_format": [
            {
                "id": "ON_SITE",
                "name": "На месте работодателя"
            }
        ],
        "working_hours": [
            {
                "id": "HOURS_12",
                "name": "12 часов"
            }
        ],
        "work_schedule_by_days": [
            {
                "id": "TWO_ON_TWO_OFF",
                "name": "2/2"
            }
        ],
        "night_shifts": false,
        "professional_roles": [
            {
                "id": "67",
                "name": "Менеджер по логистике, менеджер по ВЭД"
            }
        ],
        "accept_incomplete_resumes": false,
        "experience": {
            "id": "between1And3",
            "name": "От 1 года до 3 лет"
        },
        "employment": {
            "id": "full",
            "name": "Полная занятость"
        },
        "employment_form": {
            "id": "FULL",
            "name": "Полная"
        },
        "internship": false,
        "adv_response_url": null,
        "is_adv_vacancy": false,
        "adv_context": null
    },
    {
        "id": "121935018",
        "premium": false,
        "name": "Руководитель проектов",
        "department": {
            "id": "ozonru-2180-commerce",
            "name": "Ozon Офис и Коммерция"
        },
        "has_test": false,
        "response_letter_required": false,
        "area": {
            "id": "1",
            "name": "Москва",
            "url": "https://api.hh.ru/areas/1"
        },
        "salary": null,
        "salary_range": null,
        "type": {
            "id": "open",
            "name": "Открытая"
        },
        "address": {
            "city": "Москва",
            "street": "Пресненская набережная",
            "building": "10",
            "lat": 55.74723295660558,
            "lng": 37.536558290665916,
            "description": null,
            "raw": "Москва, Пресненская набережная, 10",
            "metro": {
                "station_name": "Деловой центр",
                "line_name": "Большая кольцевая линия",
                "station_id": "97.603",
                "line_id": "97",
                "lat": 55.7491,
                "lng": 37.5395
            },
            "metro_stations": [
                {
                    "station_name": "Деловой центр",
                    "line_name": "Большая кольцевая линия",
                    "station_id": "97.603",
                    "line_id": "97",
                    "lat": 55.7491,
                    "lng": 37.5395
                },
                {
                    "station_name": "Деловой центр",
                    "line_name": "Солнцевская",
                    "station_id": "133.468",
                    "line_id": "133",
                    "lat": 55.7491,
                    "lng": 37.5395
                },
                {
                    "station_name": "Москва-Сити",
                    "line_name": "Филевская",
                    "station_id": "4.179",
                    "line_id": "4",
                    "lat": 55.748056,
                    "lng": 37.532778
                }
            ],
            "id": "1522426"
        },
        "response_url": null,
        "sort_point_distance": null,
        "published_at": "2025-06-23T10:32:13+0300",
        "created_at": "2025-06-23T10:32:13+0300",
        "archived": false,
        "apply_alternate_url": "https://hh.ru/applicant/vacancy_response?vacancyId=121935018",
        "branding": {
            "type": "MAKEUP",
            "tariff": null
        },
        "show_logo_in_search": true,
        "show_contacts": false,
        "insider_interview": null,
        "url": "https://api.hh.ru/vacancies/121935018?host=hh.ru",
        "alternate_url": "https://hh.ru/vacancy/121935018",
        "relations": [],
        "employer": {
            "id": "2180",
            "name": "Ozon",
            "url": "https://api.hh.ru/employers/2180",
            "alternate_url": "https://hh.ru/employer/2180",
            "logo_urls": {
                "original": "https://img.hhcdn.ru/employer-logo-original/1069622.png",
                "90": "https://img.hhcdn.ru/employer-logo/5899117.png",
                "240": "https://img.hhcdn.ru/employer-logo/5899118.png"
            },
            "vacancies_url": "https://api.hh.ru/vacancies?employer_id=2180",
            "accredited_it_employer": true,
            "employer_rating": {
                "total_rating": "4.6",
                "reviews_count": 9209
            },
            "trusted": true
        },
        "snippet": {
            "requirement": "Опыт работы в роли руководителя проектов - от 3 лет. Общий опыт проектной работы - от 5 лет. Опыт реализации проектов внедрения...",
            "responsibility": "Анализ запросов от бизнеса, формулирование проектных задач, формирование бизнес- и функциональных требований. Активное участие в формировании целевого дизайна процессов, расчета..."
        },
        "contacts": null,
        "schedule": {
            "id": "fullDay",
            "name": "Полный день"
        },
        "working_days": [],
        "working_time_intervals": [],
        "working_time_modes": [],
        "accept_temporary": false,
        "fly_in_fly_out_duration": [],
        "work_format": [
            {
                "id": "ON_SITE",
                "name": "На месте работодателя"
            },
            {
                "id": "HYBRID",
                "name": "Гибрид"
            }
        ],
        "working_hours": [
            {
                "id": "HOURS_8",
                "name": "8 часов"
            }
        ],
        "work_schedule_by_days": [
            {
                "id": "FIVE_ON_TWO_OFF",
                "name": "5/2"
            }
        ],
        "night_shifts": false,
        "professional_roles": [
            {
                "id": "107",
                "name": "Руководитель проектов"
            }
        ],
        "accept_incomplete_resumes": false,
        "experience": {
            "id": "moreThan6",
            "name": "Более 6 лет"
        },
        "employment": {
            "id": "full",
            "name": "Полная занятость"
        },
        "employment_form": {
            "id": "FULL",
            "name": "Полная"
        },
        "internship": false,
        "adv_response_url": null,
        "is_adv_vacancy": false,
        "adv_context": null
    },
    {
        "id": "121068742",
        "premium": false,
        "name": "Специалист по качеству клиентской поддержки",
        "department": {
            "id": "ozonru-2180-express",
            "name": "Ozon fresh"
        },
        "has_test": false,
        "response_letter_required": false,
        "area": {
            "id": "1",
            "name": "Москва",
            "url": "https://api.hh.ru/areas/1"
        },
        "salary": null,
        "salary_range": null,
        "type": {
            "id": "open",
            "name": "Открытая"
        },
        "address": null,
        "response_url": null,
        "sort_point_distance": null,
        "published_at": "2025-06-30T10:20:12+0300",
        "created_at": "2025-06-30T10:20:12+0300",
        "archived": false,
        "apply_alternate_url": "https://hh.ru/applicant/vacancy_response?vacancyId=121068742",
        "branding": {
            "type": "MAKEUP",
            "tariff": null
        },
        "show_logo_in_search": true,
        "show_contacts": false,
        "insider_interview": null,
        "url": "https://api.hh.ru/vacancies/121068742?host=hh.ru",
        "alternate_url": "https://hh.ru/vacancy/121068742",
        "relations": [],
        "employer": {
            "id": "2180",
            "name": "Ozon",
            "url": "https://api.hh.ru/employers/2180",
            "alternate_url": "https://hh.ru/employer/2180",
            "logo_urls": {
                "original": "https://img.hhcdn.ru/employer-logo-original/1069622.png",
                "90": "https://img.hhcdn.ru/employer-logo/5899117.png",
                "240": "https://img.hhcdn.ru/employer-logo/5899118.png"
            },
            "vacancies_url": "https://api.hh.ru/vacancies?employer_id=2180",
            "accredited_it_employer": true,
            "employer_rating": {
                "total_rating": "4.6",
                "reviews_count": 9209
            },
            "trusted": true
        },
        "snippet": {
            "requirement": "Уверенное владение Excel (в том числе анализ, проверка и визуализация данных). Умение составлять отчёты и презентации. Внимательность к деталям, аккуратность...",
            "responsibility": "Ежедневно проверять корректность ответов операторов клиентского сервиса и соблюдение регламентов обработки обращений. Вести отчётность по результатам проверок и выявленным нарушениям. "
        },
        "contacts": null,
        "schedule": {
            "id": "remote",
            "name": "Удаленная работа"
        },
        "working_days": [],
        "working_time_intervals": [],
        "working_time_modes": [],
        "accept_temporary": false,
        "fly_in_fly_out_duration": [],
        "work_format": [
            {
                "id": "REMOTE",
                "name": "Удалённо"
            }
        ],
        "working_hours": [
            {
                "id": "HOURS_8",
                "name": "8 часов"
            }
        ],
        "work_schedule_by_days": [
            {
                "id": "FIVE_ON_TWO_OFF",
                "name": "5/2"
            }
        ],
        "night_shifts": false,
        "professional_roles": [
            {
                "id": "121",
                "name": "Специалист технической поддержки"
            }
        ],
        "accept_incomplete_resumes": true,
        "experience": {
            "id": "noExperience",
            "name": "Нет опыта"
        },
        "employment": {
            "id": "full",
            "name": "Полная занятость"
        },
        "employment_form": {
            "id": "FULL",
            "name": "Полная"
        },
        "internship": false,
        "adv_response_url": null,
        "is_adv_vacancy": false,
        "adv_context": null
    },
    {
        "id": "122208399",
        "premium": false,
        "name": "QA-инженер, Группа разработки \"Интеграция логистических провайдеров Express\"",
        "department": {
            "id": "ozonru-2180-dev",
            "name": "Ozon Информационные технологии"
        },
        "has_test": false,
        "response_letter_required": false,
        "area": {
            "id": "1",
            "name": "Москва",
            "url": "https://api.hh.ru/areas/1"
        },
        "salary": null,
        "salary_range": null,
        "type": {
            "id": "open",
            "name": "Открытая"
        },
        "address": {
            "city": "Москва",
            "street": "Краснопресненская набережная",
            "building": "10",
            "lat": 55.75478,
            "lng": 37.563718,
            "description": null,
            "raw": "Москва, Краснопресненская набережная, 10",
            "metro": {
                "station_name": "Москва-Сити",
                "line_name": "Филевская",
                "station_id": "4.179",
                "line_id": "4",
                "lat": 55.748056,
                "lng": 37.532778
            },
            "metro_stations": [
                {
                    "station_name": "Москва-Сити",
                    "line_name": "Филевская",
                    "station_id": "4.179",
                    "line_id": "4",
                    "lat": 55.748056,
                    "lng": 37.532778
                }
            ],
            "id": "7288889"
        },
        "response_url": null,
        "sort_point_distance": null,
        "published_at": "2025-06-30T14:20:01+0300",
        "created_at": "2025-06-30T14:20:01+0300",
        "archived": false,
        "apply_alternate_url": "https://hh.ru/applicant/vacancy_response?vacancyId=122208399",
        "branding": {
            "type": "MAKEUP",
            "tariff": null
        },
        "show_logo_in_search": true,
        "show_contacts": true,
        "insider_interview": null,
        "url": "https://api.hh.ru/vacancies/122208399?host=hh.ru",
        "alternate_url": "https://hh.ru/vacancy/122208399",
        "relations": [],
        "employer": {
            "id": "2180",
            "name": "Ozon",
            "url": "https://api.hh.ru/employers/2180",
            "alternate_url": "https://hh.ru/employer/2180",
            "logo_urls": {
                "original": "https://img.hhcdn.ru/employer-logo-original/1069622.png",
                "90": "https://img.hhcdn.ru/employer-logo/5899117.png",
                "240": "https://img.hhcdn.ru/employer-logo/5899118.png"
            },
            "vacancies_url": "https://api.hh.ru/vacancies?employer_id=2180",
            "accredited_it_employer": true,
            "employer_rating": {
                "total_rating": "4.6",
                "reviews_count": 9209
            },
            "trusted": true
        },
        "snippet": {
            "requirement": "Стек: C#, PostgreSQL, REST API, gRPC, Kafka, микросервисная архитектура, Allure. Опыт в автотестах на C# от 3х лет, также...",
            "responsibility": "Интеграция логистических провайдеров Express - сервис, позволяющий силами сторонних курьерских служб доставлять товар продавца с его склада покупателю и в ПВЗ..."
        },
        "contacts": null,
        "schedule": {
            "id": "remote",
            "name": "Удаленная работа"
        },
        "working_days": [],
        "working_time_intervals": [],
        "working_time_modes": [],
        "accept_temporary": false,
        "fly_in_fly_out_duration": [],
        "work_format": [
            {
                "id": "ON_SITE",
                "name": "На месте работодателя"
            },
            {
                "id": "REMOTE",
                "name": "Удалённо"
            },
            {
                "id": "HYBRID",
                "name": "Гибрид"
            }
        ],
        "working_hours": [
            {
                "id": "HOURS_8",
                "name": "8 часов"
            }
        ],
        "work_schedule_by_days": [
            {
                "id": "FIVE_ON_TWO_OFF",
                "name": "5/2"
            }
        ],
        "night_shifts": false,
        "professional_roles": [
            {
                "id": "40",
                "name": "Другое"
            }
        ],
        "accept_incomplete_resumes": true,
        "experience": {
            "id": "between3And6",
            "name": "От 3 до 6 лет"
        },
        "employment": {
            "id": "full",
            "name": "Полная занятость"
        },
        "employment_form": {
            "id": "FULL",
            "name": "Полная"
        },
        "internship": false,
        "adv_response_url": null,
        "is_adv_vacancy": false,
        "adv_context": null
    },
    {
        "id": "122184409",
        "premium": false,
        "name": "Делопроизводитель",
        "department": {
            "id": "ozonru-2180-express",
            "name": "Ozon fresh"
        },
        "has_test": false,
        "response_letter_required": false,
        "area": {
            "id": "53",
            "name": "Краснодар",
            "url": "https://api.hh.ru/areas/53"
        },
        "salary": {
            "from": 49500,
            "to": null,
            "currency": "RUR",
            "gross": true
        },
        "salary_range": {
            "from": 49500,
            "to": null,
            "currency": "RUR",
            "gross": true,
            "mode": {
                "id": "MONTH",
                "name": "За месяц"
            },
            "frequency": {
                "id": "TWICE_PER_MONTH",
                "name": "Два раза в месяц"
            }
        },
        "type": {
            "id": "open",
            "name": "Открытая"
        },
        "address": {
            "city": "Краснодар",
            "street": "улица Стасова",
            "building": "178",
            "lat": 45.023832,
            "lng": 39.046181,
            "description": null,
            "raw": "Краснодар, улица Стасова, 178",
            "metro": null,
            "metro_stations": [],
            "id": "6585758"
        },
        "response_url": null,
        "sort_point_distance": null,
        "published_at": "2025-06-30T09:20:35+0300",
        "created_at": "2025-06-30T09:20:35+0300",
        "archived": false,
        "apply_alternate_url": "https://hh.ru/applicant/vacancy_response?vacancyId=122184409",
        "branding": {
            "type": "MAKEUP",
            "tariff": null
        },
        "show_logo_in_search": true,
        "show_contacts": true,
        "insider_interview": null,
        "url": "https://api.hh.ru/vacancies/122184409?host=hh.ru",
        "alternate_url": "https://hh.ru/vacancy/122184409",
        "relations": [],
        "employer": {
            "id": "2180",
            "name": "Ozon",
            "url": "https://api.hh.ru/employers/2180",
            "alternate_url": "https://hh.ru/employer/2180",
            "logo_urls": {
                "original": "https://img.hhcdn.ru/employer-logo-original/1069622.png",
                "90": "https://img.hhcdn.ru/employer-logo/5899117.png",
                "240": "https://img.hhcdn.ru/employer-logo/5899118.png"
            },
            "vacancies_url": "https://api.hh.ru/vacancies?employer_id=2180",
            "accredited_it_employer": true,
            "employer_rating": {
                "total_rating": "4.6",
                "reviews_count": 9209
            },
            "trusted": true
        },
        "snippet": {
            "requirement": "Желателен опыт ведения документооборота. Уверенный пользователь ПК (в том числе Microsoft Excel). Ответственность, внимательность, коммуникабельность.",
            "responsibility": "Работа с первичной документацией. Кадровый документооборот: переводы, увольнения, отпуска. Ведение складского документооборота. Выполнение поручений непосредственного руководителя."
        },
        "contacts": null,
        "schedule": {
            "id": "fullDay",
            "name": "Полный день"
        },
        "working_days": [],
        "working_time_intervals": [],
        "working_time_modes": [],
        "accept_temporary": false,
        "fly_in_fly_out_duration": [],
        "work_format": [
            {
                "id": "ON_SITE",
                "name": "На месте работодателя"
            }
        ],
        "working_hours": [
            {
                "id": "HOURS_8",
                "name": "8 часов"
            }
        ],
        "work_schedule_by_days": [
            {
                "id": "FIVE_ON_TWO_OFF",
                "name": "5/2"
            }
        ],
        "night_shifts": false,
        "professional_roles": [
            {
                "id": "33",
                "name": "Делопроизводитель, архивариус"
            }
        ],
        "accept_incomplete_resumes": false,
        "experience": {
            "id": "between1And3",
            "name": "От 1 года до 3 лет"
        },
        "employment": {
            "id": "full",
            "name": "Полная занятость"
        },
        "employment_form": {
            "id": "FULL",
            "name": "Полная"
        },
        "internship": false,
        "adv_response_url": null,
        "is_adv_vacancy": false,
        "adv_context": null
    },
    {
        "id": "122167581",
        "premium": false,
        "name": "Стажер-бизнес аналитик",
        "department": {
            "id": "ozonru-2180-commerce",
            "name": "Ozon Офис и Коммерция"
        },
        "has_test": false,
        "response_letter_required": false,
        "area": {
            "id": "1",
            "name": "Москва",
            "url": "https://api.hh.ru/areas/1"
        },
        "salary": null,
        "salary_range": null,
        "type": {
            "id": "open",
            "name": "Открытая"
        },
        "address": null,
        "response_url": null,
        "sort_point_distance": null,
        "published_at": "2025-06-28T16:00:19+0300",
        "created_at": "2025-06-28T16:00:19+0300",
        "archived": false,
        "apply_alternate_url": "https://hh.ru/applicant/vacancy_response?vacancyId=122167581",
        "branding": {
            "type": "MAKEUP",
            "tariff": null
        },
        "show_logo_in_search": true,
        "show_contacts": false,
        "insider_interview": null,
        "url": "https://api.hh.ru/vacancies/122167581?host=hh.ru",
        "alternate_url": "https://hh.ru/vacancy/122167581",
        "relations": [],
        "employer": {
            "id": "2180",
            "name": "Ozon",
            "url": "https://api.hh.ru/employers/2180",
            "alternate_url": "https://hh.ru/employer/2180",
            "logo_urls": {
                "original": "https://img.hhcdn.ru/employer-logo-original/1069622.png",
                "90": "https://img.hhcdn.ru/employer-logo/5899117.png",
                "240": "https://img.hhcdn.ru/employer-logo/5899118.png"
            },
            "vacancies_url": "https://api.hh.ru/vacancies?employer_id=2180",
            "accredited_it_employer": true,
            "employer_rating": {
                "total_rating": "4.6",
                "reviews_count": 9209
            },
            "trusted": true
        },
        "snippet": {
            "requirement": "Готовность работать 30, 40 часов в неделю. Уверенное владение Excel. Желание разбираться в процессах и предлагать улучшения. Аналитический склад ума...",
            "responsibility": "Формирование отчетов. Работа с макросами. Анализ причин возвратов. Анализ брака в логистике."
        },
        "contacts": null,
        "schedule": {
            "id": "fullDay",
            "name": "Полный день"
        },
        "working_days": [],
        "working_time_intervals": [],
        "working_time_modes": [],
        "accept_temporary": false,
        "fly_in_fly_out_duration": [],
        "work_format": [
            {
                "id": "HYBRID",
                "name": "Гибрид"
            }
        ],
        "working_hours": [
            {
                "id": "HOURS_8",
                "name": "8 часов"
            }
        ],
        "work_schedule_by_days": [
            {
                "id": "FIVE_ON_TWO_OFF",
                "name": "5/2"
            }
        ],
        "night_shifts": false,
        "professional_roles": [
            {
                "id": "150",
                "name": "Бизнес-аналитик"
            }
        ],
        "accept_incomplete_resumes": false,
        "experience": {
            "id": "noExperience",
            "name": "Нет опыта"
        },
        "employment": {
            "id": "full",
            "name": "Полная занятость"
        },
        "employment_form": {
            "id": "FULL",
            "name": "Полная"
        },
        "internship": false,
        "adv_response_url": null,
        "is_adv_vacancy": false,
        "adv_context": null
    },
    {
        "id": "119882820",
        "premium": false,
        "name": "Сборщик заказов (г. Алматы)",
        "department": {
            "id": "ozonru-2180-boro",
            "name": "Ozon Производство"
        },
        "has_test": false,
        "response_letter_required": false,
        "area": {
            "id": "160",
            "name": "Алматы",
            "url": "https://api.hh.ru/areas/160"
        },
        "salary": {
            "from": 379500,
            "to": null,
            "currency": "KZT",
            "gross": true
        },
        "salary_range": {
            "from": 379500,
            "to": null,
            "currency": "KZT",
            "gross": true,
            "mode": {
                "id": "MONTH",
                "name": "За месяц"
            },
            "frequency": null
        },
        "type": {
            "id": "open",
            "name": "Открытая"
        },
        "address": {
            "city": "Алматы",
            "street": null,
            "building": null,
            "lat": 43.237163,
            "lng": 76.945654,
            "description": null,
            "raw": "Алматы",
            "metro": {
                "station_name": "Абая",
                "line_name": "Первая",
                "station_id": "64.433",
                "line_id": "64",
                "lat": 43.242548,
                "lng": 76.949588
            },
            "metro_stations": [
                {
                    "station_name": "Абая",
                    "line_name": "Первая",
                    "station_id": "64.433",
                    "line_id": "64",
                    "lat": 43.242548,
                    "lng": 76.949588
                },
                {
                    "station_name": "Алмалы",
                    "line_name": "Первая",
                    "station_id": "64.432",
                    "line_id": "64",
                    "lat": 43.251295,
                    "lng": 76.945456
                },
                {
                    "station_name": "Байконур",
                    "line_name": "Первая",
                    "station_id": "64.434",
                    "line_id": "64",
                    "lat": 43.240401,
                    "lng": 76.927696
                }
            ],
            "id": "16294514"
        },
        "response_url": null,
        "sort_point_distance": null,
        "published_at": "2025-06-24T04:02:11+0300",
        "created_at": "2025-06-24T04:02:11+0300",
        "archived": false,
        "apply_alternate_url": "https://hh.ru/applicant/vacancy_response?vacancyId=119882820",
        "show_logo_in_search": null,
        "show_contacts": false,
        "insider_interview": null,
        "url": "https://api.hh.ru/vacancies/119882820?host=hh.ru",
        "alternate_url": "https://hh.ru/vacancy/119882820",
        "relations": [],
        "employer": {
            "id": "2180",
            "name": "Ozon",
            "url": "https://api.hh.ru/employers/2180",
            "alternate_url": "https://hh.ru/employer/2180",
            "logo_urls": {
                "original": "https://img.hhcdn.ru/employer-logo-original/1069622.png",
                "90": "https://img.hhcdn.ru/employer-logo/5899117.png",
                "240": "https://img.hhcdn.ru/employer-logo/5899118.png"
            },
            "vacancies_url": "https://api.hh.ru/vacancies?employer_id=2180",
            "accredited_it_employer": true,
            "employer_rating": {
                "total_rating": "4.6",
                "reviews_count": 9209
            },
            "trusted": true
        },
        "snippet": {
            "requirement": "Готовность к насыщенной работе в условиях производства. Приглашаем кандидатов с опытом работы, а также без опыта работы.",
            "responsibility": "Активная работа на производственном участке. Комплектация заказов с использованием ручного терминала. Отбраковка товара при подборе."
        },
        "contacts": null,
        "schedule": {
            "id": "shift",
            "name": "Сменный график"
        },
        "working_days": [],
        "working_time_intervals": [],
        "working_time_modes": [],
        "accept_temporary": false,
        "fly_in_fly_out_duration": [],
        "work_format": [],
        "working_hours": [
            {
                "id": "HOURS_12",
                "name": "12 часов"
            }
        ],
        "work_schedule_by_days": [
            {
                "id": "TWO_ON_TWO_OFF",
                "name": "2/2"
            }
        ],
        "night_shifts": false,
        "professional_roles": [
            {
                "id": "131",
                "name": "Упаковщик, комплектовщик"
            }
        ],
        "accept_incomplete_resumes": false,
        "experience": {
            "id": "noExperience",
            "name": "Нет опыта"
        },
        "employment": {
            "id": "full",
            "name": "Полная занятость"
        },
        "employment_form": {
            "id": "FULL",
            "name": "Полная"
        },
        "internship": false,
        "adv_response_url": null,
        "is_adv_vacancy": false,
        "adv_context": null
    },
    {
        "id": "119882821",
        "premium": false,
        "name": "Сборщик заказов (г. Алматы)",
        "department": {
            "id": "ozonru-2180-boro",
            "name": "Ozon Производство"
        },
        "has_test": false,
        "response_letter_required": false,
        "area": {
            "id": "160",
            "name": "Алматы",
            "url": "https://api.hh.ru/areas/160"
        },
        "salary": {
            "from": 379500,
            "to": null,
            "currency": "KZT",
            "gross": true
        },
        "salary_range": {
            "from": 379500,
            "to": null,
            "currency": "KZT",
            "gross": true,
            "mode": {
                "id": "MONTH",
                "name": "За месяц"
            },
            "frequency": null
        },
        "type": {
            "id": "open",
            "name": "Открытая"
        },
        "address": {
            "city": "Алматы",
            "street": "микрорайон Алтай-1",
            "building": null,
            "lat": 43.345245,
            "lng": 76.987659,
            "description": null,
            "raw": "Алматы, микрорайон Алтай-1",
            "metro": null,
            "metro_stations": [],
            "id": "16629494"
        },
        "response_url": null,
        "sort_point_distance": null,
        "published_at": "2025-06-24T04:02:10+0300",
        "created_at": "2025-06-24T04:02:10+0300",
        "archived": false,
        "apply_alternate_url": "https://hh.ru/applicant/vacancy_response?vacancyId=119882821",
        "show_logo_in_search": null,
        "show_contacts": false,
        "insider_interview": null,
        "url": "https://api.hh.ru/vacancies/119882821?host=hh.ru",
        "alternate_url": "https://hh.ru/vacancy/119882821",
        "relations": [],
        "employer": {
            "id": "2180",
            "name": "Ozon",
            "url": "https://api.hh.ru/employers/2180",
            "alternate_url": "https://hh.ru/employer/2180",
            "logo_urls": {
                "original": "https://img.hhcdn.ru/employer-logo-original/1069622.png",
                "90": "https://img.hhcdn.ru/employer-logo/5899117.png",
                "240": "https://img.hhcdn.ru/employer-logo/5899118.png"
            },
            "vacancies_url": "https://api.hh.ru/vacancies?employer_id=2180",
            "accredited_it_employer": true,
            "employer_rating": {
                "total_rating": "4.6",
                "reviews_count": 9209
            },
            "trusted": true
        },
        "snippet": {
            "requirement": "Готовность к насыщенной работе в условиях производства. Приглашаем кандидатов с опытом работы, а также без опыта работы.",
            "responsibility": "Активная работа на производственном участке. Комплектация заказов с использованием ручного терминала. Отбраковка товара при подборе."
        },
        "contacts": null,
        "schedule": {
            "id": "shift",
            "name": "Сменный график"
        },
        "working_days": [],
        "working_time_intervals": [],
        "working_time_modes": [],
        "accept_temporary": false,
        "fly_in_fly_out_duration": [],
        "work_format": [],
        "working_hours": [
            {
                "id": "HOURS_12",
                "name": "12 часов"
            }
        ],
        "work_schedule_by_days": [
            {
                "id": "TWO_ON_TWO_OFF",
                "name": "2/2"
            }
        ],
        "night_shifts": false,
        "professional_roles": [
            {
                "id": "131",
                "name": "Упаковщик, комплектовщик"
            }
        ],
        "accept_incomplete_resumes": false,
        "experience": {
            "id": "noExperience",
            "name": "Нет опыта"
        },
        "employment": {
            "id": "full",
            "name": "Полная занятость"
        },
        "employment_form": {
            "id": "FULL",
            "name": "Полная"
        },
        "internship": false,
        "adv_response_url": null,
        "is_adv_vacancy": false,
        "adv_context": null
    },
    {
        "id": "119882816",
        "premium": false,
        "name": "Сотрудник склада (г. Алматы)",
        "department": {
            "id": "ozonru-2180-boro",
            "name": "Ozon Производство"
        },
        "has_test": false,
        "response_letter_required": false,
        "area": {
            "id": "160",
            "name": "Алматы",
            "url": "https://api.hh.ru/areas/160"
        },
        "salary": {
            "from": 379500,
            "to": null,
            "currency": "KZT",
            "gross": true
        },
        "salary_range": {
            "from": 379500,
            "to": null,
            "currency": "KZT",
            "gross": true,
            "mode": {
                "id": "MONTH",
                "name": "За месяц"
            },
            "frequency": null
        },
        "type": {
            "id": "open",
            "name": "Открытая"
        },
        "address": {
            "city": "Алматы",
            "street": null,
            "building": null,
            "lat": 43.237163,
            "lng": 76.945654,
            "description": null,
            "raw": "Алматы",
            "metro": {
                "station_name": "Абая",
                "line_name": "Первая",
                "station_id": "64.433",
                "line_id": "64",
                "lat": 43.242548,
                "lng": 76.949588
            },
            "metro_stations": [
                {
                    "station_name": "Абая",
                    "line_name": "Первая",
                    "station_id": "64.433",
                    "line_id": "64",
                    "lat": 43.242548,
                    "lng": 76.949588
                },
                {
                    "station_name": "Алмалы",
                    "line_name": "Первая",
                    "station_id": "64.432",
                    "line_id": "64",
                    "lat": 43.251295,
                    "lng": 76.945456
                },
                {
                    "station_name": "Байконур",
                    "line_name": "Первая",
                    "station_id": "64.434",
                    "line_id": "64",
                    "lat": 43.240401,
                    "lng": 76.927696
                }
            ],
            "id": "16294514"
        },
        "response_url": null,
        "sort_point_distance": null,
        "published_at": "2025-06-24T04:02:12+0300",
        "created_at": "2025-06-24T04:02:12+0300",
        "archived": false,
        "apply_alternate_url": "https://hh.ru/applicant/vacancy_response?vacancyId=119882816",
        "show_logo_in_search": null,
        "show_contacts": false,
        "insider_interview": null,
        "url": "https://api.hh.ru/vacancies/119882816?host=hh.ru",
        "alternate_url": "https://hh.ru/vacancy/119882816",
        "relations": [],
        "employer": {
            "id": "2180",
            "name": "Ozon",
            "url": "https://api.hh.ru/employers/2180",
            "alternate_url": "https://hh.ru/employer/2180",
            "logo_urls": {
                "original": "https://img.hhcdn.ru/employer-logo-original/1069622.png",
                "90": "https://img.hhcdn.ru/employer-logo/5899117.png",
                "240": "https://img.hhcdn.ru/employer-logo/5899118.png"
            },
            "vacancies_url": "https://api.hh.ru/vacancies?employer_id=2180",
            "accredited_it_employer": true,
            "employer_rating": {
                "total_rating": "4.6",
                "reviews_count": 9209
            },
            "trusted": true
        },
        "snippet": {
            "requirement": "Готовность к насыщенной работе в условиях производства. Приглашаем кандидатов с опытом работы, а также без опыта работы.",
            "responsibility": "Активная работа на производственном участке. Комплектация заказов с использованием ручного терминала. Отбраковка товара при подборе."
        },
        "contacts": null,
        "schedule": {
            "id": "shift",
            "name": "Сменный график"
        },
        "working_days": [],
        "working_time_intervals": [],
        "working_time_modes": [],
        "accept_temporary": false,
        "fly_in_fly_out_duration": [],
        "work_format": [],
        "working_hours": [
            {
                "id": "HOURS_12",
                "name": "12 часов"
            }
        ],
        "work_schedule_by_days": [
            {
                "id": "TWO_ON_TWO_OFF",
                "name": "2/2"
            }
        ],
        "night_shifts": false,
        "professional_roles": [
            {
                "id": "131",
                "name": "Упаковщик, комплектовщик"
            }
        ],
        "accept_incomplete_resumes": false,
        "experience": {
            "id": "noExperience",
            "name": "Нет опыта"
        },
        "employment": {
            "id": "full",
            "name": "Полная занятость"
        },
        "employment_form": {
            "id": "FULL",
            "name": "Полная"
        },
        "internship": false,
        "adv_response_url": null,
        "is_adv_vacancy": false,
        "adv_context": null
    },
    {
        "id": "119882817",
        "premium": false,
        "name": "Сотрудник склада (г. Алматы)",
        "department": {
            "id": "ozonru-2180-boro",
            "name": "Ozon Производство"
        },
        "has_test": false,
        "response_letter_required": false,
        "area": {
            "id": "160",
            "name": "Алматы",
            "url": "https://api.hh.ru/areas/160"
        },
        "salary": {
            "from": 379500,
            "to": null,
            "currency": "KZT",
            "gross": true
        },
        "salary_range": {
            "from": 379500,
            "to": null,
            "currency": "KZT",
            "gross": true,
            "mode": {
                "id": "MONTH",
                "name": "За месяц"
            },
            "frequency": null
        },
        "type": {
            "id": "open",
            "name": "Открытая"
        },
        "address": {
            "city": "Алматы",
            "street": "микрорайон Алтай-1",
            "building": null,
            "lat": 43.345245,
            "lng": 76.987659,
            "description": null,
            "raw": "Алматы, микрорайон Алтай-1",
            "metro": null,
            "metro_stations": [],
            "id": "16629494"
        },
        "response_url": null,
        "sort_point_distance": null,
        "published_at": "2025-06-24T04:02:11+0300",
        "created_at": "2025-06-24T04:02:11+0300",
        "archived": false,
        "apply_alternate_url": "https://hh.ru/applicant/vacancy_response?vacancyId=119882817",
        "show_logo_in_search": null,
        "show_contacts": false,
        "insider_interview": null,
        "url": "https://api.hh.ru/vacancies/119882817?host=hh.ru",
        "alternate_url": "https://hh.ru/vacancy/119882817",
        "relations": [],
        "employer": {
            "id": "2180",
            "name": "Ozon",
            "url": "https://api.hh.ru/employers/2180",
            "alternate_url": "https://hh.ru/employer/2180",
            "logo_urls": {
                "original": "https://img.hhcdn.ru/employer-logo-original/1069622.png",
                "90": "https://img.hhcdn.ru/employer-logo/5899117.png",
                "240": "https://img.hhcdn.ru/employer-logo/5899118.png"
            },
            "vacancies_url": "https://api.hh.ru/vacancies?employer_id=2180",
            "accredited_it_employer": true,
            "employer_rating": {
                "total_rating": "4.6",
                "reviews_count": 9209
            },
            "trusted": true
        },
        "snippet": {
            "requirement": "Готовность к насыщенной работе в условиях производства. Приглашаем кандидатов с опытом работы, а также без опыта работы.",
            "responsibility": "Активная работа на производственном участке. Комплектация заказов с использованием ручного терминала. Отбраковка товара при подборе."
        },
        "contacts": null,
        "schedule": {
            "id": "shift",
            "name": "Сменный график"
        },
        "working_days": [],
        "working_time_intervals": [],
        "working_time_modes": [],
        "accept_temporary": false,
        "fly_in_fly_out_duration": [],
        "work_format": [],
        "working_hours": [
            {
                "id": "HOURS_12",
                "name": "12 часов"
            }
        ],
        "work_schedule_by_days": [
            {
                "id": "TWO_ON_TWO_OFF",
                "name": "2/2"
            }
        ],
        "night_shifts": false,
        "professional_roles": [
            {
                "id": "131",
                "name": "Упаковщик, комплектовщик"
            }
        ],
        "accept_incomplete_resumes": false,
        "experience": {
            "id": "noExperience",
            "name": "Нет опыта"
        },
        "employment": {
            "id": "full",
            "name": "Полная занятость"
        },
        "employment_form": {
            "id": "FULL",
            "name": "Полная"
        },
        "internship": false,
        "adv_response_url": null,
        "is_adv_vacancy": false,
        "adv_context": null
    }
]